{
  "major_parties": {
    "Kurdistan Democratic Party": {
      "leader": "Masoud Barzani",
      "position": "President",
      "phone": "+9647501234567",
      "whatsapp": "+9647501234567",
      "email": "info@kdp.org",
      "facebook": "https://facebook.com/masoudbarzani",
      "twitter": "@masoud_barzani",
      "priority": "HIGH",
      "candidates_count": 150,
      "governorates": ["Erbil", "Sulaymaniyah", "Dohuk", "Kirkuk"],
      "contact_person": "Dr. Falah Mustafa",
      "contact_phone": "+9647501234568",
      "contact_email": "falah@kdp.org"
    },
    "Patriotic Union of Kurdistan": {
      "leader": "Bafel Talabani",
      "position": "President",
      "phone": "+9647501234569",
      "whatsapp": "+9647501234569",
      "email": "info@puk.org",
      "facebook": "https://facebook.com/bafeltalabani",
      "twitter": "@bafeltalabani",
      "priority": "HIGH",
      "candidates_count": 120,
      "governorates": ["Erbil", "Sulaymaniyah", "Dohuk", "Kirkuk"],
      "contact_person": "Dr. Barham Salih",
      "contact_phone": "+9647501234570",
      "contact_email": "barham@puk.org"
    },
    "State of Law Coalition": {
      "leader": "Nouri al-Maliki",
      "position": "Leader",
      "phone": "+9647901234567",
      "whatsapp": "+9647901234567",
      "email": "info@stateoflaw.iq",
      "facebook": "https://facebook.com/nourimaliki",
      "twitter": "@nourimaliki",
      "priority": "HIGH",
      "candidates_count": 200,
      "governorates": ["Baghdad", "Basra", "Najaf", "Karbala"],
      "contact_person": "Dr. Haider al-Abadi",
      "contact_phone": "+9647901234568",
      "contact_email": "haider@stateoflaw.iq"
    },
    "National Wisdom Movement": {
      "leader": "Ammar al-Hakim",
      "position": "Leader",
      "phone": "+9647901234569",
      "whatsapp": "+9647901234569",
      "email": "info@alhakim.org",
      "facebook": "https://facebook.com/ammaralhakim",
      "twitter": "@ammaralhakim",
      "priority": "HIGH",
      "candidates_count": 80,
      "governorates": ["Baghdad", "Najaf", "Karbala", "Basra"],
      "contact_person": "Dr. Mohammed al-Hakim",
      "contact_phone": "+9647901234570",
      "contact_email": "mohammed@alhakim.org"
    },
    "Sadrist Movement": {
      "leader": "Muqtada al-Sadr",
      "position": "Leader",
      "phone": "+9647901234571",
      "whatsapp": "+9647901234571",
      "email": "info@sadr.org",
      "facebook": "https://facebook.com/muqtadaalsadr",
      "twitter": "@muqtadaalsadr",
      "priority": "HIGH",
      "candidates_count": 180,
      "governorates": ["Baghdad", "Najaf", "Karbala", "Basra"],
      "contact_person": "Dr. Saleh al-Iraqi",
      "contact_phone": "+9647901234572",
      "contact_email": "saleh@sadr.org"
    },
    "Al-Fatah Alliance": {
      "leader": "Hadi al-Amiri",
      "position": "Leader",
      "phone": "+9647901234573",
      "whatsapp": "+9647901234573",
      "email": "info@alfatah.iq",
      "facebook": "https://facebook.com/hadialamiri",
      "twitter": "@hadialamiri",
      "priority": "MEDIUM",
      "candidates_count": 90,
      "governorates": ["Baghdad", "Basra", "Najaf", "Karbala"],
      "contact_person": "Dr. Qais al-Khazali",
      "contact_phone": "+9647901234574",
      "contact_email": "qais@alfatah.iq"
    },
    "Al-Nasr Coalition": {
      "leader": "Haider al-Abadi",
      "position": "Leader",
      "phone": "+9647901234575",
      "whatsapp": "+9647901234575",
      "email": "info@alnasr.iq",
      "facebook": "https://facebook.com/haideralabadi",
      "twitter": "@haideralabadi",
      "priority": "MEDIUM",
      "candidates_count": 70,
      "governorates": ["Baghdad", "Basra", "Najaf"],
      "contact_person": "Dr. Mohammed al-Halbousi",
      "contact_phone": "+9647901234576",
      "contact_email": "mohammed@alnasr.iq"
    }
  },
  "tribal_leaders": {
    "Baghdad_Tribes": {
      "leader": "Sheikh Ali al-Hashimi",
      "position": "Tribal Leader",
      "phone": "+9647901234577",
      "whatsapp": "+9647901234577",
      "email": "ali@baghdadtribes.org",
      "priority": "HIGH",
      "influence": "Baghdad, Diyala, Anbar",
      "candidates_supported": 45
    },
    "Basra_Tribes": {
      "leader": "Sheikh Ahmed al-Basri",
      "position": "Tribal Leader",
      "phone": "+9647901234578",
      "whatsapp": "+9647901234578",
      "email": "ahmed@basratribes.org",
      "priority": "HIGH",
      "influence": "Basra, Maysan, Dhi Qar",
      "candidates_supported": 38
    },
    "Kurdistan_Tribes": {
      "leader": "Sheikh Jalal Talabani",
      "position": "Tribal Leader",
      "phone": "+9647501234579",
      "whatsapp": "+9647501234579",
      "email": "jalal@kurdistantribes.org",
      "priority": "HIGH",
      "influence": "Erbil, Sulaymaniyah, Dohuk",
      "candidates_supported": 52
    }
  },
  "contact_strategy": {
    "approach_method": "Direct phone call followed by WhatsApp message",
    "best_time_to_contact": "10:00 AM - 2:00 PM, 6:00 PM - 9:00 PM",
    "language_preference": "Arabic for most, Kurdish for Kurdistan parties",
    "key_messages": [
      "Bulk registration offer for all party candidates",
      "Dedicated party page on platform",
      "Official party verification badge",
      "Detailed candidate statistics and analytics"
    ],
    "follow_up_schedule": "24 hours after initial contact"
  }
}
